odoo/addons/auth_session_timeout/README.rst
odoo/addons/auth_session_timeout/__init__.py
odoo/addons/auth_session_timeout/__manifest__.py
odoo/addons/auth_session_timeout/data/ir_config_parameter_data.xml
odoo/addons/auth_session_timeout/i18n/ar.po
odoo/addons/auth_session_timeout/i18n/auth_session_timeout.pot
odoo/addons/auth_session_timeout/i18n/ca.po
odoo/addons/auth_session_timeout/i18n/da.po
odoo/addons/auth_session_timeout/i18n/de.po
odoo/addons/auth_session_timeout/i18n/el_GR.po
odoo/addons/auth_session_timeout/i18n/es.po
odoo/addons/auth_session_timeout/i18n/es_ES.po
odoo/addons/auth_session_timeout/i18n/fi.po
odoo/addons/auth_session_timeout/i18n/fr.po
odoo/addons/auth_session_timeout/i18n/fr_CH.po
odoo/addons/auth_session_timeout/i18n/fr_FR.po
odoo/addons/auth_session_timeout/i18n/hr.po
odoo/addons/auth_session_timeout/i18n/hr_HR.po
odoo/addons/auth_session_timeout/i18n/it.po
odoo/addons/auth_session_timeout/i18n/nl.po
odoo/addons/auth_session_timeout/i18n/nl_NL.po
odoo/addons/auth_session_timeout/i18n/pt.po
odoo/addons/auth_session_timeout/i18n/pt_BR.po
odoo/addons/auth_session_timeout/i18n/ro.po
odoo/addons/auth_session_timeout/i18n/sl.po
odoo/addons/auth_session_timeout/i18n/tr.po
odoo/addons/auth_session_timeout/i18n/tr_TR.po
odoo/addons/auth_session_timeout/i18n/zh_CN.po
odoo/addons/auth_session_timeout/models/__init__.py
odoo/addons/auth_session_timeout/models/ir_config_parameter.py
odoo/addons/auth_session_timeout/models/ir_http.py
odoo/addons/auth_session_timeout/models/res_users.py
odoo/addons/auth_session_timeout/readme/CONFIGURE.rst
odoo/addons/auth_session_timeout/readme/CONTRIBUTORS.rst
odoo/addons/auth_session_timeout/readme/DESCRIPTION.rst
odoo/addons/auth_session_timeout/readme/USAGE.rst
odoo/addons/auth_session_timeout/static/description/icon.png
odoo/addons/auth_session_timeout/static/description/index.html
odoo/addons/auth_session_timeout/tests/__init__.py
odoo/addons/auth_session_timeout/tests/test_ir_config_parameter.py
odoo13_addon_auth_session_timeout-13.0.1.1.1.dist-info/METADATA
odoo13_addon_auth_session_timeout-13.0.1.1.1.dist-info/WHEEL
odoo13_addon_auth_session_timeout-13.0.1.1.1.dist-info/top_level.txt
odoo13_addon_auth_session_timeout-13.0.1.1.1.dist-info/RECORD
