Metadata-Version: 2.1
Name: odoo13-addon-auth-session-timeout
Version: 13.0.1.1.1
Summary: This module disable all inactive sessions since a given delay
Home-page: https://github.com/OCA/server-auth
Author: ACSONE SA/NV, Dhinesh D, Jesse Morgan, LasLabs, Odoo Community Association (OCA)
Author-email: support@odoo-community.org
License: AGPL-3
Platform: UNKNOWN
Classifier: Programming Language :: Python
Classifier: Framework :: Odoo
Classifier: Framework :: Odoo :: 13.0
Classifier: License :: OSI Approved :: GNU Affero General Public License v3
Requires-Python: >=3.5
Requires-Dist: odoo (<13.1dev,>=13.0a)
